accounts/__init__.py
accounts/activity_recorder_mixin.py
accounts/admin.py
accounts/apps.py
accounts/authentication.py
accounts/decorators.py
accounts/device_generator.py
accounts/forms.py
accounts/models.py
accounts/signals.py
accounts/tokens.py
accounts/urls.py
accounts/utils.py
accounts/verification.py
accounts/views.py
accounts/migrations/0001_initial.py
accounts/migrations/__init__.py
accounts/templates/accounts_base.html
accounts/templates/accounts/edit.html
accounts/templates/accounts/profile.html
accounts/templates/accounts/register.html
accounts/templates/accounts/register_done.html
accounts/templates/accounts/user/detail.html
accounts/templates/accounts/user/device_changed.html
accounts/templates/accounts/user/list.html
accounts/templates/accounts/user/activation/activate_phone.html
accounts/templates/accounts/user/activation/email.html
accounts/templates/accounts/user/activation/invalid.html
accounts/templates/accounts/user/activation/valid.html
accounts/templates/accounts/user/activation/verify_phone.html
accounts/templates/includes/_form.html
accounts/templates/includes/_message.html
accounts/templates/post_office/base_email.html
accounts/templates/post_office/accounts/activation_email.html
accounts/templates/post_office/accounts/device_changed_email.html
accounts/templates/post_office/accounts/password_reset_email.html
accounts/templates/registration/logged_out.html
accounts/templates/registration/login.html
accounts/templates/registration/password_change_done.html
accounts/templates/registration/password_change_form.html
accounts/templates/registration/password_reset_complete.html
accounts/templates/registration/password_reset_confirm.html
accounts/templates/registration/password_reset_done.html
accounts/templates/registration/password_reset_form.html
accounts/tests/__init__.py
accounts/tests/test_authentication_backends.py
accounts/tests/test_forms.py
accounts/tests/test_models.py
accounts/tests/test_views.py
accounts/tests/utils.py
django_secured_accounts-1.0.2.dist-info/LICENSE
django_secured_accounts-1.0.2.dist-info/METADATA
django_secured_accounts-1.0.2.dist-info/WHEEL
django_secured_accounts-1.0.2.dist-info/top_level.txt
django_secured_accounts-1.0.2.dist-info/RECORD
