Metadata-Version: 2.1
Name: django-secured-accounts
Version: 1.0.2
Summary: Full featured user app with built-in verification and activity stream
Home-page: https://django-secured-accounts.readthedocs.io/
Author: Ahmed Shehab
Author-email: ahbox@outlook.com
License: BSD-3-Clause
Platform: UNKNOWN
Classifier: Environment :: Web Environment
Classifier: Framework :: Django
Classifier: Framework :: Django :: 3.1
Classifier: Intended Audience :: Developers
Classifier: License :: OSI Approved :: BSD License
Classifier: Operating System :: OS Independent
Classifier: Programming Language :: Python
Classifier: Programming Language :: Python :: 3
Classifier: Programming Language :: Python :: 3.6
Classifier: Programming Language :: Python :: 3.7
Classifier: Programming Language :: Python :: 3.8
Classifier: Programming Language :: Python :: 3.9
Classifier: Topic :: Internet :: WWW/HTTP
Classifier: Topic :: Internet :: WWW/HTTP :: Dynamic Content
Requires-Dist: Django
Requires-Dist: six
Requires-Dist: Pillow
Requires-Dist: user-agents
Requires-Dist: geoip2
Requires-Dist: phonenumbers
Requires-Dist: django-phonenumber-field
Requires-Dist: maxminddb
Requires-Dist: twilio
